nikki_python/__init__.py
nikki_python/nikki_client.py
nikki_python-1.0.0.dist-info/licenses/LICENSE
nikki_python-1.0.0.dist-info/METADATA
nikki_python-1.0.0.dist-info/WHEEL
nikki_python-1.0.0.dist-info/top_level.txt
nikki_python-1.0.0.dist-info/RECORD
