Metadata-Version: 2.4
Name: nikki_python
Version: 1.0.0
Summary: initial beta version
Author-email: dev nikki <dev.nikki.build@gmail.com>
License: MIT License
Project-URL: Homepage, https://github.com/nikki-build/nikki.python
Project-URL: Bug Tracker, https://github.com/pypa/sampleproject/issues
Classifier: Programming Language :: Python :: 3
Classifier: Programming Language :: Python :: 3.8
Classifier: Programming Language :: Python :: 3.9
Classifier: Programming Language :: Python :: 3.10
Classifier: Programming Language :: Python :: 3.11
Classifier: Programming Language :: Python :: 3.12
Classifier: License :: OSI Approved :: MIT License
Classifier: Operating System :: OS Independent
Requires-Python: >=3.8
License-File: LICENSE
Requires-Dist: websockets
Dynamic: license-file
